pycounts_ugo/__init__.py
pycounts_ugo/plotting.py
pycounts_ugo/pycounts_ugo.py
pycounts_ugo-0.1.0.dist-info/LICENSE
pycounts_ugo-0.1.0.dist-info/WHEEL
pycounts_ugo-0.1.0.dist-info/METADATA
pycounts_ugo-0.1.0.dist-info/RECORD
