Metadata-Version: 2.1
Name: pycounts-ugo
Version: 0.1.0
Summary: Calculate word counts in a text file !
License: MIT
Author: Ugochukwu Onyebuchi
Requires-Python: >=3.9
Classifier: License :: OSI Approved :: MIT License
Classifier: Programming Language :: Python :: 3
Classifier: Programming Language :: Python :: 3.9
Classifier: Programming Language :: Python :: 3.10
Classifier: Programming Language :: Python :: 3.11
Requires-Dist: matplotlib (>=3.6.1,<4.0.0)
